dme/__init__.py
dme/dme.py
dme/fit_gauss_2D.py
dme/native_api.py
dme/rcc.py
dme/bin/release/dme_cpu.dll
dme/bin/release/dme_cuda.dll
dme/bin/release/libdme_cuda.so
dme/bin/release/msvcp140.dll
dme-1.0.dist-info/METADATA
dme-1.0.dist-info/WHEEL
dme-1.0.dist-info/top_level.txt
dme-1.0.dist-info/RECORD
