Metadata-Version: 2.1
Name: dme
Version: 1.0
Summary: SMLM Drift Estimation using the DME algorithm
Home-page: UNKNOWN
Author: Jelmer Cnossen
Author-email: j.cnossen@gmail.com
License: UNKNOWN
Platform: UNKNOWN
Classifier: Programming Language :: Python :: 3
Classifier: Programming Language :: C++
Classifier: License :: OSI Approved :: MIT License
Classifier: Operating System :: Microsoft :: Windows
Requires-Dist: numpy
Requires-Dist: matplotlib
Requires-Dist: tqdm
